count_files/__init__.py
count_files/__main__.py
count_files/platforms.py
count_files/settings.py
count_files/utils/__init__.py
count_files/utils/decorators.py
count_files/utils/file_handlers.py
count_files/utils/file_preview.py
count_files/utils/help_system_extension.py
count_files/utils/help_text.py
count_files/utils/viewing_modes.py
count_files-1.5.0.dist-info/LICENSE
count_files-1.5.0.dist-info/METADATA
count_files-1.5.0.dist-info/WHEEL
count_files-1.5.0.dist-info/entry_points.txt
count_files-1.5.0.dist-info/top_level.txt
count_files-1.5.0.dist-info/RECORD
