Metadata-Version: 2.1
Name: count-files
Version: 1.5.0
Summary: A command-line interface (CLI) utility that helps you count all the files or search for files with a certain file extension (or without it) in the specified directory.
Home-page: https://no-title.victordomingos.com/projects/count-files/
License: MIT
Project-URL: Documentation, https://countfiles.readthedocs.io
Project-URL: Source, https://github.com/victordomingos/Count-files
Project-URL: Bug Reports, https://github.com/victordomingos/Count-files/issues
Keywords: file count code analysis cli search extension recursive non-recursive
Platform: UNKNOWN
Classifier: Development Status :: 5 - Production/Stable 
Classifier: Environment :: Console
Classifier: Intended Audience :: Developers
Classifier: License :: OSI Approved :: MIT License
Classifier: Natural Language :: English
Classifier: Operating System :: OS Independent
Classifier: Operating System :: MacOS :: MacOS X
Classifier: Operating System :: Microsoft :: Windows
Classifier: Operating System :: POSIX :: Linux 
Classifier: Programming Language :: Python :: 3
Classifier: Programming Language :: Python :: 3.6
Classifier: Programming Language :: Python :: 3.7
Classifier: Topic :: Utilities
Classifier: Topic :: Desktop Environment :: File Managers
Classifier: Topic :: System :: Filesystems
Requires-Python: >=3.6
